snbackup/__init__.py
snbackup/__main__.py
snbackup/backup.py
snbackup/device.py
snbackup/files.py
snbackup/helpers.py
snbackup/setup.py
snbackup/utilities.py
snbackup-2.2.0.dist-info/licenses/LICENSE
snbackup-2.2.0.dist-info/METADATA
snbackup-2.2.0.dist-info/WHEEL
snbackup-2.2.0.dist-info/entry_points.txt
snbackup-2.2.0.dist-info/top_level.txt
snbackup-2.2.0.dist-info/RECORD
