Metadata-Version: 2.4
Name: snbackup
Version: 2.2.0
Summary: CLI tool to backup Supernote note files
Author-email: devdevindev <devinwrx@gmail.com>
Project-URL: Homepage, https://github.com/theburningbush/snbackup
Project-URL: Issues, https://github.com/theburningbush/snbackup/issues
Classifier: Programming Language :: Python :: 3 :: Only
Classifier: Programming Language :: Python :: 3.10
Classifier: Programming Language :: Python :: 3.11
Classifier: Programming Language :: Python :: 3.12
Classifier: Programming Language :: Python :: 3.13
Classifier: License :: OSI Approved :: Apache Software License
Classifier: Operating System :: OS Independent
Classifier: Topic :: Utilities
Requires-Python: >=3.10
License-File: LICENSE
Requires-Dist: httpx
Requires-Dist: rich
Provides-Extra: test
Requires-Dist: pytest; extra == "test"
Requires-Dist: ruff; extra == "test"
Dynamic: license-file
